gcidsum.py
gcidsum-0.1.7.dist-info/entry_points.txt
gcidsum-0.1.7.dist-info/LICENSE
gcidsum-0.1.7.dist-info/WHEEL
gcidsum-0.1.7.dist-info/METADATA
gcidsum-0.1.7.dist-info/RECORD
