Metadata-Version: 2.1
Name: gcidsum
Version: 0.1.7
Summary: 
Home-page: https://github.com/Cologler/gcidsum-python
License: MIT
Author: Cologler
Author-email: skyoflw@gmail.com
Requires-Python: >=3.8,<4.0
Classifier: License :: OSI Approved :: MIT License
Classifier: Programming Language :: Python :: 3
Classifier: Programming Language :: Python :: 3.8
Classifier: Programming Language :: Python :: 3.9
Classifier: Programming Language :: Python :: 3.10
Requires-Dist: xlgcid (>=0.1.0,<0.2.0)
